README.md
setup.py
SmartHab.egg-info/PKG-INFO
SmartHab.egg-info/SOURCES.txt
SmartHab.egg-info/dependency_links.txt
SmartHab.egg-info/requires.txt
SmartHab.egg-info/top_level.txt
pysmarthab/__init__.py
pysmarthab/device.py
pysmarthab/network.py
pysmarthab/security.py
pysmarthab/state.py