Metadata-Version: 2.1
Name: SmartHab
Version: 0.19
Summary: This package allows controlling devices in a SmartHab-powered home.
Home-page: https://gitlab.com/outadoc/python-smarthab/
Author: Baptiste Candellier
Author-email: outadoc@gmail.com
License: UNKNOWN
Platform: UNKNOWN
Classifier: Programming Language :: Python :: 3.5
Classifier: License :: OSI Approved :: GNU General Public License v3 or later (GPLv3+)
Classifier: Operating System :: OS Independent
Classifier: Topic :: Home Automation
